cassiopy/__init__.py
cassiopy/grid.py
cassiopy/mixture.py
cassiopy/stats.py
cassiopy-0.1.0.dist-info/LICENCE
cassiopy-0.1.0.dist-info/METADATA
cassiopy-0.1.0.dist-info/WHEEL
cassiopy-0.1.0.dist-info/RECORD
