Metadata-Version: 2.3
Name: cassiopy
Version: 0.1.0
Summary: A python library for clustering using skew-t mixture models.
License: MIT
Author: Maya GUY
Author-email: Maya.guy@msomg.fr
Requires-Python: >=3.8
Classifier: License :: OSI Approved :: MIT License
Classifier: Programming Language :: Python :: 3
Classifier: Programming Language :: Python :: 3.8
Classifier: Programming Language :: Python :: 3.9
Classifier: Programming Language :: Python :: 3.10
Classifier: Programming Language :: Python :: 3.11
Classifier: Programming Language :: Python :: 3.12
Classifier: Programming Language :: Python :: 3.13
Provides-Extra: docs
Requires-Dist: h5py (>=3.11.0)
Requires-Dist: joblib (>=1.4.2)
Requires-Dist: matplotlib (>=3.4.3)
Requires-Dist: numpy (>=1.25)
Requires-Dist: pandas (>=1.3.5)
Requires-Dist: scikit-learn (>=1.5.1)
Requires-Dist: scipy (>=1.10)
Requires-Dist: seaborn (>=0.12)
